reminiscence/__init__.py
reminiscence/cache.py
reminiscence/config.py
reminiscence/core.py
reminiscence/decorators.py
reminiscence/scheduler.py
reminiscence/types.py
reminiscence/api/__init__.py
reminiscence/api/routes.py
reminiscence/api/server.py
reminiscence/compression/__init__.py
reminiscence/compression/base.py
reminiscence/compression/factory.py
reminiscence/compression/gzip.py
reminiscence/compression/zstd.py
reminiscence/embeddings/__init__.py
reminiscence/embeddings/base.py
reminiscence/embeddings/fastembed.py
reminiscence/embeddings/model_registry.py
reminiscence/embeddings/models.yaml
reminiscence/encryption/__init__.py
reminiscence/encryption/age.py
reminiscence/encryption/base.py
reminiscence/encryption/kms.py
reminiscence/encryption/registry.py
reminiscence/encryption/vault.py
reminiscence/eviction/__init__.py
reminiscence/eviction/base.py
reminiscence/eviction/fifo.py
reminiscence/eviction/lfu.py
reminiscence/eviction/lru.py
reminiscence/metrics/__init__.py
reminiscence/metrics/exporters.py
reminiscence/metrics/tracker.py
reminiscence/operations/__init__.py
reminiscence/operations/invalidation.py
reminiscence/operations/lookup.py
reminiscence/operations/maintenance.py
reminiscence/operations/storage_ops.py
reminiscence/serialization/__init__.py
reminiscence/serialization/base.py
reminiscence/serialization/pipeline.py
reminiscence/serialization/serializer.py
reminiscence/storage/__init__.py
reminiscence/storage/base.py
reminiscence/storage/converters.py
reminiscence/storage/lancedb.py
reminiscence/storage/schemas.py
reminiscence/utils/__init__.py
reminiscence/utils/fingerprint.py
reminiscence/utils/logging.py
reminiscence/utils/query_detection.py
reminiscence-0.5.0.dist-info/licenses/LICENSE
reminiscence-0.5.0.dist-info/METADATA
reminiscence-0.5.0.dist-info/WHEEL
reminiscence-0.5.0.dist-info/top_level.txt
reminiscence-0.5.0.dist-info/RECORD
