Metadata-Version: 2.4
Name: reminiscence
Version: 0.5.0
Summary: Semantic caching for LLMs
Author: Juan José de las Heras Herrera
Requires-Python: >=3.9
License-File: LICENSE
Requires-Dist: lancedb>=0.25.1
Requires-Dist: orjson>=3.11.3
Requires-Dist: pyarrow>=21.0.0
Requires-Dist: structlog>=25.4.0
Requires-Dist: pyyaml>=6.0
Requires-Dist: fastembed>=0.3.0
Requires-Dist: pyrage>=1.3.0
Requires-Dist: zstandard>=0.25.0
Requires-Dist: pybase64>=1.4.2
Provides-Extra: dataframes
Requires-Dist: pandas>=2.0.0; extra == "dataframes"
Requires-Dist: polars>=0.19.0; extra == "dataframes"
Requires-Dist: numpy>=1.24.0; extra == "dataframes"
Provides-Extra: otel
Requires-Dist: opentelemetry-api<2.0.0,>=1.20.0; extra == "otel"
Requires-Dist: opentelemetry-sdk<2.0.0,>=1.20.0; extra == "otel"
Requires-Dist: opentelemetry-exporter-otlp-proto-http<2.0.0,>=1.20.0; extra == "otel"
Provides-Extra: dev
Requires-Dist: pytest>=7.4.0; extra == "dev"
Requires-Dist: pytest-cov>=4.1.0; extra == "dev"
Requires-Dist: pandas>=2.0.0; extra == "dev"
Provides-Extra: full
Requires-Dist: pandas>=2.0.0; extra == "full"
Requires-Dist: polars>=0.19.0; extra == "full"
Requires-Dist: numpy>=1.24.0; extra == "full"
Requires-Dist: opentelemetry-api<2.0.0,>=1.20.0; extra == "full"
Requires-Dist: opentelemetry-sdk<2.0.0,>=1.20.0; extra == "full"
Requires-Dist: opentelemetry-exporter-otlp-proto-http<2.0.0,>=1.20.0; extra == "full"
Dynamic: license-file
